culebrONT/__init__.py
culebrONT/_version.py
culebrONT/culebront_logo.png
culebrONT/global_variables.py
culebrONT/main.py
culebrONT/module.py
culebrONT/containers/Dockerfile_test
culebrONT/containers/apptainer.culebront_tools.def
culebrONT/install_files/config.yaml
culebrONT/install_files/configfile.yaml
culebrONT/install_files/tools_path.yaml
culebrONT/install_files/config_test/config_A.yaml
culebrONT/install_files/config_test/config_AC.yaml
culebrONT/install_files/config_test/config_AP.yaml
culebrONT/install_files/config_test/config_APC.yaml
culebrONT/install_files/config_test/config_APCQ-CIRQ.yaml
culebrONT/install_files/config_test/config_APCQ.yaml
culebrONT/install_files/config_test/config_APQ.yaml
culebrONT/install_files/config_test/config_quick.yaml
culebrONT/schemas/config.schema.yaml
culebrONT/schemas/tools_path.schemas.yaml
culebrONT/scripts/__init__.py
culebrONT/scripts/controllingMapping.py
culebrONT/snakefiles/Snakefile
culebrONT/snakefiles/assemblers.snake
culebrONT/snakefiles/circular.snake
culebrONT/snakefiles/correction.snake
culebrONT/snakefiles/polishers.snake
culebrONT/snakefiles/quality.snake
culebrONT/snakefiles/reported.snake
culebrONT/snakemake_scripts/Report.Rmd
culebrONT/snakemake_scripts/assembly-stats.py
culebrONT/snakemake_scripts/edit_quarto.py
culebrONT/snakemake_scripts/generate_samples.py
culebrONT/snakemake_scripts/generate_tools.py
culebrONT/snakemake_scripts/get_benchmark.py
culebrONT/snakemake_scripts/get_stats_busco.py
culebrONT/snakemake_scripts/get_stats_flagstats.py
culebrONT/snakemake_scripts/makerange.py
culebrONT/snakemake_scripts/rotateCircSeqs.R
culebrONT/snakemake_scripts/run_mauve.py
culebrONT/snakemake_scripts/tagCircSeq.R
culebrONT/snakemake_scripts/report_template/_quarto.yml
culebrONT/snakemake_scripts/report_template/cellalina.csl
culebrONT/snakemake_scripts/report_template/index.qmd
culebrONT/snakemake_scripts/report_template/references.bib
culebrONT/snakemake_scripts/report_template/references.qmd
culebront-4.0.0.dist-info/licenses/LICENCE
culebront-4.0.0.dist-info/METADATA
culebront-4.0.0.dist-info/WHEEL
culebront-4.0.0.dist-info/entry_points.txt
culebront-4.0.0.dist-info/top_level.txt
culebront-4.0.0.dist-info/RECORD
