Metadata-Version: 2.4
Name: culebrONT
Version: 4.0.0
Summary: CulebrONT is an open-source, scalable, modular and traceable Snakemake pipeline, able to launch multiple
Author: Tram Vi Bao (IRD)
Author-email: "Orjuela Julie (IRD)" <julie.orjuela@ird.fr>, "Comte Aurore (IRD)" <aurore.comte@ird.fr>, "Ravel Sebastien (CIRAD)" <sebastien.ravel@cirad.fr>, "Charriat Florian (INRAE)" <florian.charriat@cirad.fr>, "Sabot François (IRD)" <francois.sabot@ird.fr>, "Cunnac Sebastien (IRD)" <sebastien.cunnac@ird.fr>
Maintainer-email: "Orjuela Julie (IRD)" <julie.orjuela@ird.fr>, "Comte Aurore (IRD)" <aurore.comte@ird.fr>, "Ravel Sebastien (CIRAD)" <sebastien.ravel@cirad.fr>, "Charriat Florian (INRAE)" <florian.charriat@cirad.fr>
License:                     GNU GENERAL PUBLIC LICENSE
Project-URL: Homepage, https://forge.ird.fr/diade/culebront_pipeline
Project-URL: Downloads, https://forge.ird.fr/diade/culebront_pipeline/archive/
Project-URL: Bug Tracker, https://forge.ird.fr/diade/culebront_pipeline/issues
Project-URL: Documentation, https://snakecdysis.readthedocs.io/en/latest/
Project-URL: Source Code, https://forge.ird.fr/diade/culebront_pipeline
Keywords: snakemake,assembly,workflow,HPC
Classifier: License :: OSI Approved :: GNU General Public License v3 or later (GPLv3+)
Classifier: License :: CeCILL-C Free Software License Agreement (CECILL-C)
Classifier: License :: Free for non-commercial use
Classifier: Development Status :: 5 - Production/Stable
Classifier: Intended Audience :: Developers
Classifier: Intended Audience :: End Users/Desktop
Classifier: Operating System :: POSIX :: Linux
Classifier: Programming Language :: Python :: 3.12
Classifier: Natural Language :: English
Classifier: Topic :: Scientific/Engineering
Classifier: Topic :: Scientific/Engineering :: Bio-Informatics
Classifier: Topic :: Software Development :: Assemblers
Requires-Python: >=3.12
License-File: LICENCE
Requires-Dist: pandas
Requires-Dist: matplotlib
Requires-Dist: tabulate
Requires-Dist: ipython
Requires-Dist: biopython
Requires-Dist: pysam
Requires-Dist: numpy
Requires-Dist: nbformat
Requires-Dist: snakecdysis>=2.0.0
Provides-Extra: doc
Requires-Dist: sphinx_click; extra == "doc"
Requires-Dist: sphinx_copybutton; extra == "doc"
Requires-Dist: sphinx_rtd_theme; extra == "doc"
Requires-Dist: tox; extra == "doc"
Provides-Extra: dev
Requires-Dist: setuptools>=68.2.0; extra == "dev"
Requires-Dist: setuptools_scm[toml]>=8.0.0; extra == "dev"
Requires-Dist: build>=1.0.0; extra == "dev"
Dynamic: license-file
